src/traffic_light.v
module traffic_light(
    input wire clk,
    input wire rst,
    output reg [1:0] light   // 00=紅, 01=綠, 10=黃
);
    // 狀態編碼
    localparam RED    = 2'b00;
    localparam GREEN  = 2'b01;
    localparam YELLOW = 2'b10;

    reg [1:0] state, next_state;

    // 狀態暫存器 (時序邏輯)
    always @(posedge clk or posedge rst) begin
        if (rst)
            state <= RED;          // Reset 初始為紅燈
        else
            state <= next_state;   // 狀態更新
    end

    // 狀態轉換邏輯 (組合邏輯)
    always @(*) begin
        case(state)
            RED:    next_state = GREEN;
            GREEN:  next_state = YELLOW;
            YELLOW: next_state = RED;
            default: next_state = RED;
        endcase
    end

    // 輸出邏輯 (燈號)
    always @(*) begin
        light = state;
    end
endmodule

tb/tb_traffic_light.v
module tb_traffic_light;
    reg clk, rst;
    wire [1:0] light;

    traffic_light uut (.clk(clk), .rst(rst), .light(light));

    // 產生時脈 (10ns 週期)
    always #5 clk = ~clk;

    initial begin
        $dumpfile("tb_traffic_light.vcd");
        $dumpvars(0, tb_traffic_light);

        clk = 0; rst = 1;
        #10 rst = 0;               // 釋放 reset

        // 模擬 10 個狀態切換
        repeat(10) @(posedge clk);

        $finish;
    end
endmodule

tb_traffic_light.vcd
$date
	Fri Aug  8 14:08:51 2025
$end
$version
	Icarus Verilog
$end
$timescale
	1s
$end
$scope module tb_traffic_light $end
$var wire 2 ! light [1:0] $end
$var reg 1 " clk $end
$var reg 1 # rst $end
$scope module uut $end
$var wire 1 " clk $end
$var wire 1 # rst $end
$var parameter 2 $ GREEN $end
$var parameter 2 % RED $end
$var parameter 2 & YELLOW $end
$var reg 2 ' light [1:0] $end
$var reg 2 ( next_state [1:0] $end
$var reg 2 ) state [1:0] $end
$upscope $end
$upscope $end
$enddefinitions $end
$comment Show the parameter values. $end
$dumpall
b10 &
b0 %
b1 $
$end
#0
$dumpvars
b0 )
b1 (
b0 '
1#
0"
b0 !
$end
#5
1"
#10
0"
0#
#15
b10 (
b1 !
b1 '
b1 )
1"
#20
0"
#25
b10 !
b10 '
b0 (
b10 )
1"
#30
0"
#35
b1 (
b0 !
b0 '
b0 )
1"
#40
0"
#45
b1 !
b1 '
b10 (
b1 )
1"
#50
0"
#55
b0 (
b10 !
b10 '
b10 )
1"
#60
0"
#65
b0 !
b0 '
b1 (
b0 )
1"
#70
0"
#75
b10 (
b1 !
b1 '
b1 )
1"
#80
0"
#85
b10 !
b10 '
b0 (
b10 )
1"
#90
0"
#95
b1 (
b0 !
b0 '
b0 )
1"
#100
0"
#105
b1 !
b1 '
b10 (
b1 )
1"
