src/and3_gate.v
// 3 input and gate
module and3_gate(
    input wire a, b, c,
    output wire y
);
    assign y = a & b & c;
endmodule

tb/tb_and3_gate.v
module tb_and3_gate;
    reg a, b, c;
    wire y;
    and3_gate uut (.a(a), .b(b), .c(c), .y(y));

    initial begin
        $monitor("a=%b b=%b c=%b y=%b", a, b, c, y);
        $dumpfile("sim/tb_and3_gate.vcd");
        $dumpvars(0, tb_and3_gate);

        a=0; b=0; c=0; #1;
        a=0; b=0; c=1; #1;
        a=0; b=1; c=0; #1;
        a=0; b=1; c=1; #1;
        a=1; b=0; c=0; #1;
        a=1; b=0; c=1; #1;
        a=1; b=1; c=0; #1;
        a=1; b=1; c=1; #1;

        $finish;
    end
endmodule

sim/tb_and3_gate.vcd
$date
	Mon Aug  4 17:42:40 2025
$end
$version
	Icarus Verilog
$end
$timescale
	1s
$end
$scope module tb_and3_gate $end
$var wire 1 ! y $end
$var reg 1 " a $end
$var reg 1 # b $end
$var reg 1 $ c $end
$scope module uut $end
$var wire 1 " a $end
$var wire 1 # b $end
$var wire 1 $ c $end
$var wire 1 ! y $end
$upscope $end
$upscope $end
$enddefinitions $end
$comment Show the parameter values. $end
$dumpall
$end
#0
$dumpvars
0$
0#
0"
0!
$end
#1
1$
#2
0$
1#
#3
1$
#4
0$
0#
1"
#5
1$
#6
0$
1#
#7
1!
1$
