src/counter.v
module counter(
    input wire clk,
    input wire rst,
    output reg [3:0]count
);
    always @(posedge clk or posedge rst) begin
        if(rst)
            count <= 4'd0;
        else
            count <= count + 1;
    end
endmodule

tb/tb_counter.v
module tb_counter;
    reg clk, rst;
    wire [3:0]count;

    counter uut(
        .clk(clk),
        .rst(rst),
        .count(count)
    );

    always #1 clk = ~clk;
    initial begin
        $monitor("time:%t clk:%d rst:%d count:%d", $time, clk, rst, count);
        $dumpfile("sim/tb_counter.vcd");
        $dumpvars(0, tb_counter);

        clk=0; rst=1;
        #1 rst=0;
        #35 rst=1;
        #1 rst=0;
        #10 $finish;

    end
endmodule

sim/tb_counter.vcd
$date
	Tue Aug  5 16:33:59 2025
$end
$version
	Icarus Verilog
$end
$timescale
	1s
$end
$scope module tb_counter $end
$var wire 4 ! count [3:0] $end
$var reg 1 " clk $end
$var reg 1 # rst $end
$scope module uut $end
$var wire 1 " clk $end
$var wire 1 # rst $end
$var reg 4 $ count [3:0] $end
$upscope $end
$upscope $end
$enddefinitions $end
$comment Show the parameter values. $end
$dumpall
$end
#0
$dumpvars
b0 $
1#
0"
b0 !
$end
#1
b1 !
b1 $
0#
1"
#2
0"
#3
b10 !
b10 $
1"
#4
0"
#5
b11 !
b11 $
1"
#6
0"
#7
b100 !
b100 $
1"
#8
0"
#9
b101 !
b101 $
1"
#10
0"
#11
b110 !
b110 $
1"
#12
0"
#13
b111 !
b111 $
1"
#14
0"
#15
b1000 !
b1000 $
1"
#16
0"
#17
b1001 !
b1001 $
1"
#18
0"
#19
b1010 !
b1010 $
1"
#20
0"
#21
b1011 !
b1011 $
1"
#22
0"
#23
b1100 !
b1100 $
1"
#24
0"
#25
b1101 !
b1101 $
1"
#26
0"
#27
b1110 !
b1110 $
1"
#28
0"
#29
b1111 !
b1111 $
1"
#30
0"
#31
b0 !
b0 $
1"
#32
0"
#33
b1 !
b1 $
1"
#34
0"
#35
b10 !
b10 $
1"
#36
b0 !
b0 $
0"
1#
#37
b1 !
b1 $
1"
0#
#38
0"
#39
b10 !
b10 $
1"
#40
0"
#41
b11 !
b11 $
1"
#42
0"
#43
b100 !
b100 $
1"
#44
0"
#45
b101 !
b101 $
1"
#46
0"
#47
b110 !
b110 $
1"
