src/dff.v
module dff(
    input wire d,
    input wire clk, 
    input wire rst,
    output reg q //用reg才能在always賦值
);
   always @(posedge clk or posedge rst) begin //非同步reset
        if(rst)
            q <= 1'b0; 
        else
            q <= d;
   end
endmodule

tb/tb_dff.v
module tb_dff;
    reg clk, d, rst;
    wire q;
    dff uut(
        .clk(clk),
        .d(d),
        .rst(rst),
        .q(q)
    );
    always #1 clk = ~clk; //5ns轉一次
    initial begin
        $monitor("Time=%0t | clk=%b rst=%b d=%b q=%b", $time, clk, rst, d, q);
        $dumpfile("sim/tb_dff.vcd");
        $dumpvars(0, tb_dff);

        clk=0; d=0; rst=1;
        #2 rst = 0;             // 釋放 reset
        #2 d = 1;               // 在下一個時脈邊緣，q 變成 1
        #2 d = 0;               // 下一個時脈邊緣，q 變回 0
        #4 d = 1;               // 維持高電位兩個週期
        #4 rst = 1;             // 再次 reset
        #2 rst = 0;

        #4 $finish;
    end
endmodule

sim/tb_dff.vcd
$date
	Tue Aug  5 15:58:32 2025
$end
$version
	Icarus Verilog
$end
$timescale
	1s
$end
$scope module tb_dff $end
$var wire 1 ! q $end
$var reg 1 " clk $end
$var reg 1 # d $end
$var reg 1 $ rst $end
$scope module uut $end
$var wire 1 " clk $end
$var wire 1 # d $end
$var wire 1 $ rst $end
$var reg 1 ! q $end
$upscope $end
$upscope $end
$enddefinitions $end
$comment Show the parameter values. $end
$dumpall
$end
#0
$dumpvars
1$
0#
0"
0!
$end
#1
1"
#2
0"
0$
#3
1"
#4
0"
1#
#5
1!
1"
#6
0"
0#
#7
0!
1"
#8
0"
#9
1"
#10
0"
1#
#11
1!
1"
#12
0"
#13
1"
#14
0!
0"
1$
#15
1"
#16
0"
0$
#17
1!
1"
