src/FIFO.v
module FIFO(
    input wire clk, rst, rd_en, wr_en,
    input wire [7:0] din,
    output reg [7:0] dout,
    output wire empty, full

);
    reg [7:0] mem [0:15];
    reg [4:0] w_ptr, r_ptr;

    always @(posedge clk or posedge rst) begin //write
        if(rst) w_ptr <= 0; 
        else begin
            if(wr_en && !full) begin
                mem[w_ptr[3:0]] <= din;
                w_ptr <= w_ptr+1;
            end
        end
    end

    always @(posedge clk or posedge rst) begin
        if(rst) r_ptr <= 0;
        else if (rd_en && !empty) begin
            dout <= mem[r_ptr[3:0]];
            r_ptr <= r_ptr+1;
        end
    end

    assign empty = (w_ptr == r_ptr);
    assign full =  (w_ptr[3:0] == r_ptr[3:0]) && (w_ptr[4] != r_ptr[4]);
endmodule

tb/tb_FIFO.v
module tb_FIFO;
    reg clk, rst, rd_en, wr_en;
    reg[7:0] din;
    wire[7:0] dout;
    wire empty, full;

    FIFO uut(.clk(clk), .rst(rst), .rd_en(rd_en), .wr_en(wr_en), .din(din), .dout(dout), .empty(empty), .full(full));
    
    always #1 clk = ~clk;
    initial begin
        $dumpfile("sim/tb_FIFO.vcd");
        $dumpvars(0, tb_FIFO);
        rst=1; clk=0; rd_en=0; wr_en=0;
        #2 rst=0;
        repeat(4) begin
            @(posedge clk);
            wr_en = 1;
            din = $random;
        end
        @(posedge clk) wr_en = 0;

        repeat(4) begin
            @(posedge clk);
            rd_en = 1;
        end
        @(posedge clk) rd_en = 0;

        repeat(2) begin
            @(posedge clk);
            wr_en = 1;
            din = $random;
            rd_en = 1;
        end
        @(posedge clk) rd_en=0; wr_en=0;

        $finish;
    end

endmodule

sim/tb_FIFO.vcd
$date
	Sun Aug 24 18:18:47 2025
$end
$version
	Icarus Verilog
$end
$timescale
	1s
$end
$scope module tb_FIFO $end
$var wire 1 ! full $end
$var wire 1 " empty $end
$var wire 8 # dout [7:0] $end
$var reg 1 $ clk $end
$var reg 8 % din [7:0] $end
$var reg 1 & rd_en $end
$var reg 1 ' rst $end
$var reg 1 ( wr_en $end
$scope module uut $end
$var wire 1 $ clk $end
$var wire 8 ) din [7:0] $end
$var wire 1 ! full $end
$var wire 1 & rd_en $end
$var wire 1 ' rst $end
$var wire 1 ( wr_en $end
$var wire 1 " empty $end
$var reg 8 * dout [7:0] $end
$var reg 5 + r_ptr [4:0] $end
$var reg 5 , w_ptr [4:0] $end
$upscope $end
$upscope $end
$enddefinitions $end
$comment Show the parameter values. $end
$dumpall
$end
#0
$dumpvars
b0 ,
b0 +
bx *
bx )
0(
1'
0&
bx %
0$
bx #
1"
0!
$end
#1
1$
#2
0$
0'
#3
0"
b1 ,
b100100 %
b100100 )
1(
1$
#4
0$
#5
b10 ,
b10000001 %
b10000001 )
1$
#6
0$
#7
b11 ,
b1001 %
b1001 )
1$
#8
0$
#9
b100 ,
b1100011 %
b1100011 )
1$
#10
0$
#11
0(
1$
#12
0$
#13
b1 +
b100100 #
b100100 *
1&
1$
#14
0$
#15
b10 +
b10000001 #
b10000001 *
1$
#16
0$
#17
b11 +
b1001 #
b1001 *
1$
#18
0$
#19
1"
b100 +
b1100011 #
b1100011 *
1$
#20
0$
#21
0&
1$
#22
0$
#23
0"
b101 ,
1&
b1101 %
b1101 )
1(
1$
#24
0$
#25
b101 +
b1101 #
b1101 *
b110 ,
b10001101 %
b10001101 )
1$
#26
0$
#27
0(
0&
1$
