src/mux2to1.v
module mux2to1(
    input wire a,b,
    input wire sel,
    output wire y
);
    assign y = sel ? a : b;
endmodule

tb/tb_mux2to1.v
module tb_mux2to1;
    reg a , b;
    reg sel;
    wire y;
    mux2to1 uut (.a(a), .b(b), .sel(sel), .y(y));

    initial begin
        $monitor("sel=%d a=%d b=%d y=%d", sel, a, b, y);
        $dumpfile("sim/tb_mux2to1.vcd");
        $dumpvars(0, tb_mux2to1);

        sel=0; a=0; b=0; #1;
        sel=1; a=0; b=0; #1;
        sel=0; a=0; b=1; #1;
        sel=1; a=0; b=1; #1;
        sel=0; a=1; b=0; #1;
        sel=1; a=1; b=0; #1;
        sel=0; a=1; b=1; #1;
        sel=1; a=1; b=1; #1;

        $finish;
    end
endmodule

sim/tb_mux2to1.vcd
$date
	Tue Aug  5 14:38:23 2025
$end
$version
	Icarus Verilog
$end
$timescale
	1s
$end
$scope module tb_mux2to1 $end
$var wire 1 ! y $end
$var reg 1 " a $end
$var reg 1 # b $end
$var reg 1 $ sel $end
$scope module uut $end
$var wire 1 " a $end
$var wire 1 # b $end
$var wire 1 $ sel $end
$var wire 1 ! y $end
$upscope $end
$upscope $end
$enddefinitions $end
$comment Show the parameter values. $end
$dumpall
$end
#0
$dumpvars
0$
0#
0"
0!
$end
#1
1$
#2
1!
1#
0$
#3
0!
1$
#4
0#
1"
0$
#5
1!
1$
#6
1#
0$
#7
1$
