src/traffic_light_ped.v
/*
題目描述：行人按鈕控制紅燈延長
📌 規格
狀態依序為：RED → GREEN → YELLOW → RED
每個燈號停留時間：
狀態	時間
RED	    5 秒（正常）
        → 若有行人按鈕 ped_btn=1，變成 8 秒
GREEN	3 秒
YELLOW	2 秒
*/
module traffic_light_ped(
    input wire clk, rst, ped_btn,
    output reg [1:0] light
);
    reg [1:0] state, next_state;
    reg [3:0] timer;
    localparam RED = 2'b00;
    localparam GREEN = 2'b01;
    localparam YELLOW = 2'b10;

    always @(posedge clk or posedge rst) begin
        if(rst) begin
            state <= RED;
            timer <= 0;
        end else begin
            if(state != next_state)
                timer <= 0;
            else
                timer <= timer + 1;
            state <= next_state;
        end
    end

    always @(*) begin
        case(state)
            RED: 
                if(timer < (ped_btn ? 8 : 5))
                    next_state = RED;
                else
                    next_state = GREEN;
            GREEN:
                if(timer < 3)
                    next_state = GREEN;
                else 
                    next_state = YELLOW;
            YELLOW:
                if(timer < 2)
                    next_state = YELLOW;
                else
                    next_state = RED;
            default: next_state = RED;
        endcase
    end

    always @(*) begin 
        light = state;
    end
endmodule

tb/tb_traffic_light_ped.v
module tb_traffic_light_ped;
    reg clk, rst, ped_btn;
    wire [1:0]light;
    traffic_light_ped uut(.clk(clk), .rst(rst), .ped_btn(ped_btn), .light(light));

    always #1 clk = ~clk;
    initial begin
        $dumpfile("sim/tb_traffic_light_ped.vcd");
        $dumpvars(0, tb_traffic_light_ped);

        rst = 1; clk = 0; ped_btn = 0;
        #2 rst = 0;
        repeat(20) @(posedge clk);
        rst = 1;
        #2 rst = 0; ped_btn=1;
        repeat(20) @(posedge clk);

        $finish;
    end
endmodule

sim/tb_traffic_light_ped.vcd
$date
	Fri Aug  8 17:02:34 2025
$end
$version
	Icarus Verilog
$end
$timescale
	1s
$end
$scope module tb_traffic_light_ped $end
$var wire 2 ! light [1:0] $end
$var reg 1 " clk $end
$var reg 1 # ped_btn $end
$var reg 1 $ rst $end
$scope module uut $end
$var wire 1 " clk $end
$var wire 1 # ped_btn $end
$var wire 1 $ rst $end
$var parameter 2 % GREEN $end
$var parameter 2 & RED $end
$var parameter 2 ' YELLOW $end
$var reg 2 ( light [1:0] $end
$var reg 2 ) next_state [1:0] $end
$var reg 2 * state [1:0] $end
$var reg 4 + timer [3:0] $end
$upscope $end
$upscope $end
$enddefinitions $end
$comment Show the parameter values. $end
$dumpall
b10 '
b0 &
b1 %
$end
#0
$dumpvars
b0 +
b0 *
b0 )
b0 (
1$
0#
0"
b0 !
$end
#1
1"
#2
0"
0$
#3
b1 +
1"
#4
0"
#5
b10 +
1"
#6
0"
#7
b11 +
1"
#8
0"
#9
b100 +
1"
#10
0"
#11
b1 )
b101 +
1"
#12
0"
#13
b1 !
b1 (
b1 *
b0 +
1"
#14
0"
#15
b1 +
1"
#16
0"
#17
b10 +
1"
#18
0"
#19
b10 )
b11 +
1"
#20
0"
#21
b10 !
b10 (
b10 *
b0 +
1"
#22
0"
#23
b1 +
1"
#24
0"
#25
b0 )
b10 +
1"
#26
0"
#27
b0 !
b0 (
b0 *
b0 +
1"
#28
0"
#29
b1 +
1"
#30
0"
#31
b10 +
1"
#32
0"
#33
b11 +
1"
#34
0"
#35
b100 +
1"
#36
0"
#37
b1 )
b101 +
1"
#38
0"
#39
b1 !
b1 (
b1 *
b0 +
1"
#40
0"
#41
b0 !
b0 (
b0 )
b0 *
1$
1"
#42
0"
#43
b1 +
1"
1#
0$
#44
0"
#45
b10 +
1"
#46
0"
#47
b11 +
1"
#48
0"
#49
b100 +
1"
#50
0"
#51
b101 +
1"
#52
0"
#53
b110 +
1"
#54
0"
#55
b111 +
1"
#56
0"
#57
b1 )
b1000 +
1"
#58
0"
#59
b1 !
b1 (
b1 *
b0 +
1"
#60
0"
#61
b1 +
1"
#62
0"
#63
b10 +
1"
#64
0"
#65
b10 )
b11 +
1"
#66
0"
#67
b10 !
b10 (
b10 *
b0 +
1"
#68
0"
#69
b1 +
1"
#70
0"
#71
b0 )
b10 +
1"
#72
0"
#73
b0 !
b0 (
b0 *
b0 +
1"
#74
0"
#75
b1 +
1"
#76
0"
#77
b10 +
1"
#78
0"
#79
b11 +
1"
#80
0"
#81
b100 +
1"
