src/traffic_light_timer.v
/*
設計紅綠燈 FSM，狀態依序為 RED → GREEN → YELLOW → RED，
但每個燈必須維持特定時間：
狀態	停留時間
RED	    5 秒
GREEN	3 秒
YELLOW	2 秒
條件：
輸入 clk 是 1Hz（每秒 1 個脈波）
請加入 reg [2:0] timer 來幫助倒數
當倒數結束時才轉移狀態
✅ 你需要設計：
localparam 狀態名稱
加入 timer 控制每個狀態停留時間
三段式 FSM
*/
module traffic_light_timer(
    input wire clk, rst,
    output reg [1:0] light
);
    reg [2:0] timer;
    reg [1:0] state, next_state;

    localparam RED = 2'b00;
    localparam GREEN = 2'b01;
    localparam YELLOW = 2'b10;

    always @(posedge clk or posedge rst) begin
        if(rst) begin
            state <= RED;
            timer <= 0;
        end else begin
            if(state != next_state)
                timer <= 0;
            else
                timer <= timer + 1;
            state <= next_state;
        end
    end

    always @(*) begin 
        case(state)
            RED : 
                if(timer < 5-1) 
                    next_state = RED;
                else
                    next_state = GREEN;
            GREEN:
                if(timer < 3-1)
                    next_state = GREEN;
                else
                    next_state = YELLOW;
            YELLOW:
                if(timer < 2-1)
                    next_state = YELLOW;
                else
                    next_state = RED;
        endcase
    end

    always @(*) begin
        light = state;
    end

endmodule

tb/tb_traffic_light_timer.v
module tb_traffic_light_timer;
    reg clk;
    reg rst;
    wire [1:0] light;

    traffic_light_timer uut(.clk(clk), .rst(rst), .light(light));
    always #1 clk = ~clk;
    initial begin
        $monitor("light = %h", light);
        $dumpfile("sim/tb_traffic_light_timer.vcd");
        $dumpvars(0, tb_traffic_light_timer);

        rst = 1; clk = 0;
        #2 rst = 0;
        repeat(20) @(posedge clk);
        $finish;
    end
endmodule

sim/tb_traffic_light_timer.vcd
$date
	Fri Aug  8 15:36:49 2025
$end
$version
	Icarus Verilog
$end
$timescale
	1s
$end
$scope module tb_traffic_light_timer $end
$var wire 2 ! light [1:0] $end
$var reg 1 " clk $end
$var reg 1 # rst $end
$scope module uut $end
$var wire 1 " clk $end
$var wire 1 # rst $end
$var parameter 2 $ GREEN $end
$var parameter 2 % RED $end
$var parameter 2 & YELLOW $end
$var reg 2 ' light [1:0] $end
$var reg 2 ( next_state [1:0] $end
$var reg 2 ) state [1:0] $end
$var reg 3 * timer [2:0] $end
$upscope $end
$upscope $end
$enddefinitions $end
$comment Show the parameter values. $end
$dumpall
b10 &
b0 %
b1 $
$end
#0
$dumpvars
b0 *
b0 )
b0 (
b0 '
1#
0"
b0 !
$end
#1
1"
#2
0"
0#
#3
b1 *
1"
#4
0"
#5
b10 *
1"
#6
0"
#7
b11 *
1"
#8
0"
#9
b1 (
b100 *
1"
#10
0"
#11
b1 !
b1 '
b1 )
b0 *
1"
#12
0"
#13
b1 *
1"
#14
0"
#15
b10 (
b10 *
1"
#16
0"
#17
b10 !
b10 '
b10 )
b0 *
1"
#18
0"
#19
b0 (
b1 *
1"
#20
0"
#21
b0 !
b0 '
b0 )
b0 *
1"
#22
0"
#23
b1 *
1"
#24
0"
#25
b10 *
1"
#26
0"
#27
b11 *
1"
#28
0"
#29
b1 (
b100 *
1"
#30
0"
#31
b1 !
b1 '
b1 )
b0 *
1"
#32
0"
#33
b1 *
1"
#34
0"
#35
b10 (
b10 *
1"
#36
0"
#37
b10 !
b10 '
b10 )
b0 *
1"
#38
0"
#39
b0 (
b1 *
1"
#40
0"
#41
b0 !
b0 '
b0 )
b0 *
1"
