src/updown_counter.v
module updown_counter(
    input wire clk,
    input wire rst,
    input wire updown,
    output reg [3:0]count
);
    always @(posedge clk or posedge rst) begin
        if(rst) 
            count <= 4'd0;
        else if(updown)
            count <= count+1;
        else
            count <= count-1;
    end
endmodule

tb/tb_updown_counter.v
module tb_updown_counter;
    reg clk, rst, updown;
    wire [3:0]count;

    updown_counter uut (
        .clk(clk),
        .rst(rst),
        .updown(updown),
        .count(count)
    );
    always #1 clk = ~clk;
    initial begin
        clk=0; rst=1; updown=1;
        $monitor("time:%t clk:%d rst:%d updown:%d count:%d", $time, clk, rst, updown, count);
        $dumpfile("sim/tb_updown_counter.vcd");
        $dumpvars(0, tb_updown_counter);

        #2 rst=0;
        #35 updown=0;
        #10 updown=1;
        #16 rst=1;
        #2 rst=0;
        #30 $finish;
    end
endmodule

sim/tb_updown_counter.vcd
$date
	Tue Aug  5 17:04:49 2025
$end
$version
	Icarus Verilog
$end
$timescale
	1s
$end
$scope module tb_updown_counter $end
$var wire 4 ! count [3:0] $end
$var reg 1 " clk $end
$var reg 1 # rst $end
$var reg 1 $ updown $end
$scope module uut $end
$var wire 1 " clk $end
$var wire 1 # rst $end
$var wire 1 $ updown $end
$var reg 4 % count [3:0] $end
$upscope $end
$upscope $end
$enddefinitions $end
$comment Show the parameter values. $end
$dumpall
$end
#0
$dumpvars
b0 %
1$
1#
0"
b0 !
$end
#1
1"
#2
0"
0#
#3
b1 !
b1 %
1"
#4
0"
#5
b10 !
b10 %
1"
#6
0"
#7
b11 !
b11 %
1"
#8
0"
#9
b100 !
b100 %
1"
#10
0"
#11
b101 !
b101 %
1"
#12
0"
#13
b110 !
b110 %
1"
#14
0"
#15
b111 !
b111 %
1"
#16
0"
#17
b1000 !
b1000 %
1"
#18
0"
#19
b1001 !
b1001 %
1"
#20
0"
#21
b1010 !
b1010 %
1"
#22
0"
#23
b1011 !
b1011 %
1"
#24
0"
#25
b1100 !
b1100 %
1"
#26
0"
#27
b1101 !
b1101 %
1"
#28
0"
#29
b1110 !
b1110 %
1"
#30
0"
#31
b1111 !
b1111 %
1"
#32
0"
#33
b0 !
b0 %
1"
#34
0"
#35
b1 !
b1 %
1"
#36
0"
#37
b0 !
b0 %
1"
0$
#38
0"
#39
b1111 !
b1111 %
1"
#40
0"
#41
b1110 !
b1110 %
1"
#42
0"
#43
b1101 !
b1101 %
1"
#44
0"
#45
b1100 !
b1100 %
1"
#46
0"
#47
b1101 !
b1101 %
1"
1$
#48
0"
#49
b1110 !
b1110 %
1"
#50
0"
#51
b1111 !
b1111 %
1"
#52
0"
#53
b0 !
b0 %
1"
#54
0"
#55
b1 !
b1 %
1"
#56
0"
#57
b10 !
b10 %
1"
#58
0"
#59
b11 !
b11 %
1"
#60
0"
#61
b100 !
b100 %
1"
#62
0"
#63
b0 !
b0 %
1"
1#
#64
0"
#65
b1 !
b1 %
1"
0#
#66
0"
#67
b10 !
b10 %
1"
#68
0"
#69
b11 !
b11 %
1"
#70
0"
#71
b100 !
b100 %
1"
#72
0"
#73
b101 !
b101 %
1"
#74
0"
#75
b110 !
b110 %
1"
#76
0"
#77
b111 !
b111 %
1"
#78
0"
#79
b1000 !
b1000 %
1"
#80
0"
#81
b1001 !
b1001 %
1"
#82
0"
#83
b1010 !
b1010 %
1"
#84
0"
#85
b1011 !
b1011 %
1"
#86
0"
#87
b1100 !
b1100 %
1"
#88
0"
#89
b1101 !
b1101 %
1"
#90
0"
#91
b1110 !
b1110 %
1"
#92
0"
#93
b1111 !
b1111 %
1"
#94
0"
#95
b0 !
b0 %
1"
